Workbook

Sheet Сводка
A1: Аренда квартир Самарканд — сводный финансовый отчёт
A2: Период: 01.01.2026 – 22.08.2026 (расходы партнёра переданы по 30.06.2026)
A4: КУРС ПЕРЕСЧЁТА — поставь свой актуальный курс, всё ниже пересчитается само
A5: UZS за 1 USD | B5: 12700
A7: 1. ОФИЦИАЛЬНЫЙ ПРОВЕРЯЕМЫЙ ДОХОД (Booking + Airbnb, обе квартиры)
A8: Источник | B8: Броней | C8: Ночей | D8: Доход $ (netto, после комиссии платформы)
A9: Booking.com (статус OK) | B9: 67 | C9: 114 | D9: 3906.96
A10: Airbnb (оплаченные брони) | B10: 20 | C10: 47 | D10: 2092.65
A11: доп.: выплата по диспуту Airbnb (сверх брони) | D11: 102
A12: ИТОГО официальный доход (без диспута) | B12: =B9+B10 | C12: =C9+C10 | D12: =D9+D10
A14: 2. РАСХОДЫ ПО ТАБЛИЦЕ ПАРТНЁРА (январь–июнь 2026)
A15: Категория | B15: Сумма, сум | C15: ≈ $, по курсу выше
A16: Все расходы (аренда, уборка, быт и т.д.) | B16: 143845780 | C16: =B16/$B$5
A17: из них разовые ('вложения'/обустройство) | B17: 38122800 | C17: =B17/$B$5
A18: из них периодические (аренда, коммуналка, уборка) | B18: =B16-B17 | C18: =B18/$B$5
A20: 3. ИТОГ: ПРИБЫЛЬ / УБЫТОК ПО ОФИЦИАЛЬНЫМ ДАННЫМ
A21: Официальный доход $ | B21: Расходы $ (по курсу) | C21: Прибыль(+) / Убыток(-) $
A22: =D12 | B22: =C16 | C22: =A22-B22
A23: Отрицательное число = по проверяемым платформенным деньгам бизнес пока НЕ окупается и не в плюсе.
A24: Это не значит, что реальных денег нет — см. лист 'Чёрная касса': минимум $1 574 подтверждённого дохода одной из квартир записано партнёром как $0.
A26: 4. ГЛАВНАЯ НАХОДКА
A27: В таблице партнёра квартира 'Black Pearl' (= Spacious apartment / Registan) три месяца подряд — апрель, май, июнь — показывает официально подтверждённые брони Booking.com, а записанный доход по ним каждый месяц: 0 сум / $0.
A28: 'White Pearl' (= квартира у аэропорта) за те же месяцы отражена в этой же таблице подробно и построчно, вплоть до Airbnb-выплат в долларах.
A29: Подробности и прямая сверка с датами Booking.com — на листе 'Чёрная касса'.

Sheet Чёрная касса
A1: Black Pearl (Spacious apartment) — доход, записанный партнёром как $0
A2: Каждая строка ниже — ночи, которые сам партнёр отметил как занятые в своей таблице ('Черная'), и которые день-в-день совпадают с официальными подтверждёнными бронями Booking.com. В колонке дохода партнёр при этом поставил 0.
A4: Месяц | B4: Ночей отмечено ('Черная') | C4: из них подтверждено Booking.com, $ | D4: + нал/'сарафанное радио', ночей (без суммы) | E4: Записано в таблице партнёра, $
A5: Апрель | B5: 20 | C5: 863.01 | D5: 0 | E5: 0
A6: Май | B6: 13 | C6: 483.59 | D6: 7 | E6: 0
A7: Июнь | B7: 8 | C7: 227.8 | D7: 15 | E7: 0
A8: ИТОГО (апр-июнь) | B8: =SUM(B5:B7) | C8: =SUM(C5:C7) | D8: =SUM(D5:D7) | E8: 0
A10: Что это значит:
A11: Минимум $1,574.40 — это НЕ предположение, это официальная сумма из выгрузки Booking.com за подтверждённые (OK) брони этой квартиры за апрель-июнь.
A12: Плюс ещё 22 ночей отмечены как занятые через нал/'сарафанное радио' — по ним партнёр вообще не указал никакой суммы, даже примерной.
A13: Для сравнения: квартира 'White Pearl' (у аэропорта) в этой же таблице учтена вплоть до отдельной брони и суммы в долларах/сумах, без пропусков.
A15: Как проверить самому
A16: 1. Открой файл 'Бронирования_2026-01-01_2026-08-22.xls' (в этой же папке проекта в Obsidian) и отфильтруй по объекту 'Spacious apartment 15 min to Registan' и статусу OK.
A17: 2. Сверь даты заезда за апрель-июнь с датами в таблице партнёра ('Черная', второй блок столбцов на листе 'Доходы') — они совпадают день в день.
A18: 3. Спроси у партнёра прямо: куда делись деньги по этим подтверждённым Booking.com броням, если в общей таблице по ним стоит 0.

Sheet По объектам
A1: Доход и расход по каждой квартире
A2: Курс берётся с листа 'Сводка' (поменяешь там — пересчитается и тут).
A4: Квартира | B4: Доход Booking+Airbnb, $ (netto) | C4: Расходы, сум | D4: Расходы, $ (по курсу) | E4: Прибыль(+)/Убыток(-), $
A5: Black Pearl (Spacious/Registan) | B5: 3534.24 | C5: 88005130 | D5: =C5/Сводка!$B$5 | E5: =B5-D5
A6: White Pearl (у аэропорта) | B6: 2465.37 | C6: 46577650 | D6: =C6/Сводка!$B$5 | E6: =B6-D6
A7: Общие расходы (не привязаны к одной квартире) | B7: 0 | C7: 9263000 | D7: =C7/Сводка!$B$5 | E7: =B7-D7
A8: ИТОГО | B8: =B5+B6+B7 | C8: =C5+C6+C7 | D8: =D5+D6+D7 | E8: =E5+E6+E7
A10: По официальным (проверяемым) деньгам обе квартиры сейчас в убытке — ожидаемо, если часть реальной выручки проходит мимо этого учёта (см. лист 'Чёрная касса').
A11: Доход Black Pearl тут — ТОЛЬКО официально подтверждённый (без учёта $0-записей из 'Чёрной кассы'). Если бы партнёр учёл все подтверждённые Booking-брони, убыток Black Pearl был бы меньше минимум на $1 574.

Sheet Окупаемость
A1: Помесячная динамика: расходы vs официальный доход
A2: Официальный доход по месяцам — по дате заезда (Booking) / дате брони (Airbnb), обе квартиры вместе. Курс — с листа 'Сводка'.
A4: Месяц | B4: Расходы, сум | C4: Расходы, $ | D4: Официальный доход, $ | E4: Разница за месяц, $ | F4: Накопительно, $
A5: Январь | B5: 39985000 | C5: =B5/Сводка!$B$5 | D5: 230.12 | E5: =D5-C5 | F5: =E5
A6: Февраль | B6: 5931250 | C6: =B6/Сводка!$B$5 | D6: 400.51 | E6: =D6-C6 | F6: =F5+E6
A7: Март | B7: 38951780 | C7: =B7/Сводка!$B$5 | D7: 1107.34 | E7: =D7-C7 | F7: =F6+E7
A8: Апрель | B8: 19213750 | C8: =B8/Сводка!$B$5 | D8: 1070.78 | E8: =D8-C8 | F8: =F7+E8
A9: Май | B9: 16411000 | C9: =B9/Сводка!$B$5 | D9: 1468.31 | E9: =D9-C9 | F9: =F8+E9
A10: Июнь | B10: 23353000 | C10: =B10/Сводка!$B$5 | D10: 1001.33 | E10: =D10-C10 | F10: =F9+E10
A11: ИТОГО (янв-июнь) | B11: =SUM(B5:B10) | C11: =SUM(C5:C10) | D11: =SUM(D5:D10) | E11: =SUM(E5:E10) | F11: =F10
A13: Июль / август — расходы партнёром не переданы (не значит, что их нет!), поэтому в накопительную кривую выше не включены:
A14: Месяц | B14: Расходы, сум | C14: Официальный доход, $
A15: Июль | B15: нет данных | C15: 242.9
A16: Август (до 22) | B16: нет данных | C16: 478.32
A18: Колонка 'Накопительно' — если уходит глубже в минус, а не поднимается к нулю, значит официальные деньги пока не покрывают расходы бизнеса.
